[{"Name": "乡长的工作服", "id": "diamond_chestplate", "lore": "看起来挺合身;但实际上似乎有的地方线头没剪掉;有点戳人", "attributes": {"maxHealth": "+5", "attackDamage": "-5", "armor": "-5", "attackSpeed": "-30%", "movementSpeed": "-25%", "armorToughness": "", "knockbackResistance": ""}, "part": "胸甲", "unbreakable": "否", "hides": {"ATTRIBUTES": 0, "ENCHANTS": 0, "DESTROYS": 0, "PLACED_ON": 0, "POTION_EFFECTS": 0, "UNBREAKABLE": 0}, "Enchantment": [{"id": "unbreaking", "lvl": 1}, {"id": "efficiency", "lvl": 1}]}, {"Name": "兔子的工作服", "id": "diamond_chestplate", "lore": "看起来挺合身;但实际上似乎有的地方线头没剪掉;有点戳人", "attributes": {"maxHealth": "+5", "attackDamage": "-5", "armor": "-5", "attackSpeed": "-30%", "movementSpeed": "-25%", "armorToughness": "", "knockbackResistance": ""}, "part": "胸甲", "unbreakable": "否", "hides": {"ATTRIBUTES": 0, "ENCHANTS": 0, "DESTROYS": 0, "PLACED_ON": 0, "POTION_EFFECTS": 0, "UNBREAKABLE": 0}, "Enchantment": [{"id": "unbreaking", "lvl": 1}, {"id": "efficiency", "lvl": 1}]}, {"Name": "安酱的帽子", "id": "diamond_helmet", "lore": "一顶鸭舌帽;安酱很喜欢戴着它去种树苗", "attributes": {"maxHealth": "", "attackDamage": "", "armor": "", "attackSpeed": "", "movementSpeed": "", "armorToughness": "+5%", "knockbackResistance": ""}, "part": "头盔", "unbreakable": "是", "hides": {"ATTRIBUTES": 0, "ENCHANTS": 0, "DESTROYS": 0, "PLACED_ON": 0, "POTION_EFFECTS": 0, "UNBREAKABLE": 0}, "Enchantment": [{"id": "protection", "lvl": 4}]}]